ertai/__init__.py
ertai/card.py
ertai/creature.py
ertai/mana.py
ertai-0.0.3.dist-info/LICENSE
ertai-0.0.3.dist-info/WHEEL
ertai-0.0.3.dist-info/METADATA
ertai-0.0.3.dist-info/RECORD
