Metadata-Version: 2.1
Name: ertai
Version: 0.0.3
Summary: A tool for mathematical analysis of Magic the Gathering
Home-page: https://vknight.org
Author: Vincent Knight
Author-email: vince@vknight.org
Requires-Python: >=3.8
Classifier: License :: OSI Approved :: MIT License
